parliament/__init__.py
parliament/__main__.py
parliament/decorators.py
parliament/invocation.py
parliament/server.py
parliament/version.py
parliament_functions-0.1.0.dist-info/LICENSE
parliament_functions-0.1.0.dist-info/METADATA
parliament_functions-0.1.0.dist-info/WHEEL
parliament_functions-0.1.0.dist-info/entry_points.txt
parliament_functions-0.1.0.dist-info/top_level.txt
parliament_functions-0.1.0.dist-info/RECORD
