Metadata-Version: 2.1
Name: parliament-functions
Version: 0.1.0
Summary: A framework for invoking functions over HTTP
Home-page: https://github.com/boson-project/parliament
Author: Lance Ball
Author-email: lball@redhat.com
License: MIT
Keywords: faas,functions,openshift
Platform: UNKNOWN
